Metadata-Version: 2.1
Name: sshscript
Version: 2.0.2
Summary: Write Python scripts to automate SSH and subprocess operations.
Home-page: https://github.com/iapyeh/sshscript
Author: Hsin Yuan Yeh
Author-email: iapyeh@gmail.com
License: MIT
Project-URL: Bug Tracker, https://github.com/iapyeh/sshscript/issues
Keywords: pypi,sshscript,ssh,paramiko,subprocess,shell script
Classifier: Development Status :: 4 - Beta
Classifier: Intended Audience :: Developers
Classifier: Intended Audience :: System Administrators
Classifier: Topic :: Software Development :: Code Generators
Classifier: Topic :: Utilities
Classifier: License :: OSI Approved :: MIT License
Classifier: Operating System :: POSIX
Classifier: Programming Language :: Python :: 3
Classifier: Programming Language :: Python :: 3 :: Only
Classifier: Programming Language :: Python :: 3.6
Classifier: Programming Language :: Python :: 3.7
Classifier: Programming Language :: Python :: 3.8
Classifier: Programming Language :: Python :: 3.9
Classifier: Programming Language :: Python :: 3.10
Requires-Python: >=3.8
License-File: LICENSE.txt
